flet_dstring/__init__.py
flet_dstring/dstring.py
flet_dstring-0.1.1.dist-info/LICENSE
flet_dstring-0.1.1.dist-info/METADATA
flet_dstring-0.1.1.dist-info/WHEEL
flet_dstring-0.1.1.dist-info/top_level.txt
flet_dstring-0.1.1.dist-info/RECORD
