Metadata-Version: 2.1
Name: flet_dstring
Version: 0.1.1
Summary: DString (Dynamic String) is a Python library that provides a simple and intuitive syntax for creating richly styled text in Flet applications.
Author: Barkin MADDOX
License-File: LICENSE
Requires-Dist: flet>=0.25.2
